django_custom_jsonfield/__init__.py
django_custom_jsonfield/fields.py
django_custom_jsonfield/rest_framework/__init__.py
django_custom_jsonfield/rest_framework/openapi.py
django_custom_jsonfield/rest_framework/serializers.py
django_custom_jsonfield-1.3.dist-info/LICENSE
django_custom_jsonfield-1.3.dist-info/METADATA
django_custom_jsonfield-1.3.dist-info/WHEEL
django_custom_jsonfield-1.3.dist-info/top_level.txt
django_custom_jsonfield-1.3.dist-info/RECORD
