Metadata-Version: 2.1
Name: django_custom_jsonfield
Version: 1.3
Summary: An extended JSON field for Django and DRF with validation support using jsonschema.
License: MIT
Project-URL: Homepage, https://github.com/AlexPetul/django_custom_jsonfield
Project-URL: Code, https://github.com/AlexPetul/django_custom_jsonfield
Classifier: Programming Language :: Python
Classifier: Programming Language :: Python :: 3
Classifier: Programming Language :: Python :: 3 :: Only
Classifier: Programming Language :: Python :: 3.8
Classifier: Programming Language :: Python :: 3.9
Classifier: Programming Language :: Python :: 3.10
Classifier: Programming Language :: Python :: 3.11
Classifier: Programming Language :: Python :: 3.12
Classifier: Intended Audience :: Developers
Classifier: Topic :: Internet
Classifier: Topic :: Software Development :: Libraries :: Python Modules
Classifier: Topic :: Software Development :: Libraries
Classifier: Topic :: Software Development
Requires-Python: >=3.8
License-File: LICENSE
Requires-Dist: django <5.1,>=4.0
Requires-Dist: jsonschema <5,>=4.0
Provides-Extra: drf
Requires-Dist: djangorestframework <3.16,>=3.13.0 ; extra == 'drf'
Requires-Dist: drf-spectacular ; extra == 'drf'
